CHANGELOG.txt
LICENSE.txt
MANIFEST.in
README.txt
__init__.py
setup.py
hi.egg-info/SOURCES.txt
hi.egg-info/dependency_links.txt
hi.egg-info/top_level.txt
hi_pypi_practice.egg-info/PKG-INFO
hi_pypi_practice.egg-info/SOURCES.txt
hi_pypi_practice.egg-info/dependency_links.txt
hi_pypi_practice.egg-info/top_level.txt
venv/Lib/site-packages/_distutils_hack/__init__.py
venv/Lib/site-packages/pip/__init__.py
venv/Lib/site-packages/pip-21.0.1.dist-info/LICENSE.txt
venv/Lib/site-packages/pip-21.0.1.dist-info/entry_points.txt
venv/Lib/site-packages/pip-21.0.1.dist-info/top_level.txt
venv/Lib/site-packages/pip/_internal/__init__.py
venv/Lib/site-packages/pip/_internal/cli/__init__.py
venv/Lib/site-packages/pip/_internal/commands/__init__.py
venv/Lib/site-packages/pip/_internal/distributions/__init__.py
venv/Lib/site-packages/pip/_internal/index/__init__.py
venv/Lib/site-packages/pip/_internal/models/__init__.py
venv/Lib/site-packages/pip/_internal/network/__init__.py
venv/Lib/site-packages/pip/_internal/operations/__init__.py
venv/Lib/site-packages/pip/_internal/operations/build/__init__.py
venv/Lib/site-packages/pip/_internal/operations/install/__init__.py
venv/Lib/site-packages/pip/_internal/req/__init__.py
venv/Lib/site-packages/pip/_internal/resolution/__init__.py
venv/Lib/site-packages/pip/_internal/resolution/legacy/__init__.py
venv/Lib/site-packages/pip/_internal/resolution/resolvelib/__init__.py
venv/Lib/site-packages/pip/_internal/utils/__init__.py
venv/Lib/site-packages/pip/_internal/vcs/__init__.py
venv/Lib/site-packages/pip/_vendor/__init__.py
venv/Lib/site-packages/pip/_vendor/vendor.txt
venv/Lib/site-packages/pip/_vendor/cachecontrol/__init__.py
venv/Lib/site-packages/pip/_vendor/cachecontrol/caches/__init__.py
venv/Lib/site-packages/pip/_vendor/certifi/__init__.py
venv/Lib/site-packages/pip/_vendor/chardet/__init__.py
venv/Lib/site-packages/pip/_vendor/chardet/cli/__init__.py
venv/Lib/site-packages/pip/_vendor/chardet/metadata/__init__.py
venv/Lib/site-packages/pip/_vendor/colorama/__init__.py
venv/Lib/site-packages/pip/_vendor/distlib/__init__.py
venv/Lib/site-packages/pip/_vendor/distlib/_backport/__init__.py
venv/Lib/site-packages/pip/_vendor/html5lib/__init__.py
venv/Lib/site-packages/pip/_vendor/html5lib/_trie/__init__.py
venv/Lib/site-packages/pip/_vendor/html5lib/filters/__init__.py
venv/Lib/site-packages/pip/_vendor/html5lib/treeadapters/__init__.py
venv/Lib/site-packages/setuptools-53.0.0.dist-info/dependency_links.txt
venv/Lib/site-packages/setuptools-53.0.0.dist-info/entry_points.txt
venv/Lib/site-packages/setuptools-53.0.0.dist-info/top_level.txt
